{
    "5736449": {
        "Description": "Признание комиссара полиции прокурору республики / Confessione di un commissario di polizia al procuratore della repubblica (Damiano Damiani / Дамиано Дамиани) [1971, Италия, драма, детектив, BDRip] Dub + MVO + original",
        "Downloads": 20,
        "Seeders": "1",
        "Leechers": "2",
        "GB": "1.45 GB",
        "pic_url": "https://i109.fastpic.ru/big/2019/0504/83/214be3769dff09b60290c0c40ad77383.jpg"
    },
    "5735931": {
        "Description": "Отель \"Империал\" / Hotel Imperial (Мориц Стиллер / Mauritz Stiller) [1927, США, драма, военный, немое кино, DVDRip] Интертитры Eng + Sub Rus",
        "Downloads": 58,
        "Seeders": "3",
        "Leechers": "0",
        "GB": "1.1 GB",
        "pic_url": "https://i109.fastpic.ru/big/2019/0524/18/fe9ed8333d68212a6351c9628fc02418.jpg"
    },
    "5736319": {
        "Description": "Проект \"Охотник за тенью\" 4 / Охота на пришельца / Shadowchaser: The Gates of Time / Orion's Key (Марк Роупер / Mark Roper) [1996, США, Фантастический боевик, DVDRip] AVO (Андрей Дольский) + Original Eng",
        "Downloads": 37,
        "Seeders": "2",
        "Leechers": "1",
        "GB": "1.4 GB",
        "pic_url": "https://i5.imageban.ru/out/2019/05/25/b77f1ae7996ed196524618b805158837.jpg"
    },
    "5728926": {
        "Description": "Компания Хьюго / Hugo Pool (Роберт Дауни Ст. / Robert Downey Sr.) [1997, США, мелодрама, комедия, DVDRemux] [Fullscreen] AVO (Визгунов) + Original (Eng) + Sub (Eng)",
        "Downloads": 92,
        "Seeders": "1",
        "Leechers": "0",
        "GB": "4.04 GB",
        "pic_url": "https://c.radikal.ru/c24/1905/4e/c7f71f3e74c9.jpg"
    },
    "5736213": {
        "Description": "Со скоростью выстрела / Загадка фотоаппарата / Shutterspeed (Марк Собель / Mark Sobel) [2000, Канада, Боевик, HDTVRip] DVO (Garsų Pasaulis) + Original Eng",
        "Downloads": 62,
        "Seeders": "3",
        "Leechers": "1",
        "GB": "1.37 GB",
        "pic_url": "https://i1.imageban.ru/out/2019/05/25/7de25eceb6b6b70bd5483bd10295a054.png"
    },
    "5736147": {
        "Description": "Тень сомнения / Shadow of a doubt (Брайан Деннехи / Brian Dennehy) [1995, США, Криминал, драма, DVDRip-AVC] DVO (НТВ плюс) + Original Eng",
        "Downloads": 49,
        "Seeders": "6",
        "Leechers": "4",
        "GB": "1.41 GB",
        "pic_url": "https://i5.imageban.ru/out/2019/05/25/7d0404942c09808a58ce12b314b5c2fe.png"
    },
    "5735961": {
        "Description": "Шелли снова в деле: Часть 1 / Wiener Dog Nationals (Кеван Петерсон / Kevan Peterson) [2013, США, комедия, семейный, спорт, WEBRip] [Локализованный видеоряд] MVO",
        "Downloads": 28,
        "Seeders": "1",
        "Leechers": "1",
        "GB": "1.46 GB",
        "pic_url": "https://i5.imageban.ru/out/2019/05/24/f6ee342d751a810831ce0b78d1072744.jpg"
    },
    "5735830": {
        "Description": "Рубеж мира / Rim of the World (МакДжи / McG) [2019, США, фантастика, боевик, комедия, приключения, WEB-DLRip] Dub (Пифагор)",
        "Downloads": 3954,
        "Seeders": "958",
        "Leechers": "190",
        "GB": "1.46 GB",
        "pic_url": "https://i1.imageban.ru/out/2019/05/24/7b8d4d9d23ca162dd32eb7038cb8d780.jpg"
    },
    "5736057": {
        "Description": "Кладбище домашних животных / Pet Sematary (Кевин Колш / Kevin Kolsh, Деннис Уидмайер / Dennis Widmeyer) [2019, США, ужасы, триллер, WEBRip] MVO (HDrezka Studio)",
        "Downloads": 3049,
        "Seeders": "303",
        "Leechers": "55",
        "GB": "1.46 GB",
        "pic_url": "https://i4.imageban.ru/out/2019/05/25/7b4be44932e352eea485b3afc75ffb30.jpg"
    },
    "5736242": {
        "Description": "Рубеж мира / Rim of the World (МакДжи / McG) [2019, США, фантастика, боевик, комедия, приключения, WEB-DLRip] Dub (Пифагор)",
        "Downloads": 373,
        "Seeders": "38",
        "Leechers": "4",
        "GB": "743.4 MB",
        "pic_url": "https://i110.fastpic.ru/big/2019/0525/5b/b5a266f9972094c3ee5ae99cba8d2b5b.jpg"
    }
}